coco_rasa/__init__.py
coco_rasa/coco_rasa.py
coco_rasa-0.0.3.dist-info/LICENSE
coco_rasa-0.0.3.dist-info/METADATA
coco_rasa-0.0.3.dist-info/WHEEL
coco_rasa-0.0.3.dist-info/top_level.txt
coco_rasa-0.0.3.dist-info/RECORD
